README.rst
setup.py
github_contributors/__init__.py
github_contributors.egg-info/PKG-INFO
github_contributors.egg-info/SOURCES.txt
github_contributors.egg-info/dependency_links.txt
github_contributors.egg-info/entry_points.txt
github_contributors.egg-info/requires.txt
github_contributors.egg-info/top_level.txt