Metadata-Version: 1.1
Name: github-contributors
Version: 0.1.0
Summary: github info of contributors
Home-page: https://github.com/juanpabloaj/github-contributors.git
Author: JuanPablo AJ
Author-email: jpabloaj@gmail.com
License: MIT
Platform: UNKNOWN
Classifier: Programming Language :: Python :: 2.7
